lib/__init__.py
lib/bamreader.py
lib/clipread.py
lib/couple.py
lib/gff.py
lib/invertedrepeat.py
lib/position.py
lib/temporalfile.py
lib/variables.py
lib/writer.py
panisa-0.1.7.data/scripts/ISFinder_search.py
panisa-0.1.7.data/scripts/panISa.py
panisa-0.1.7.dist-info/LICENSE
panisa-0.1.7.dist-info/METADATA
panisa-0.1.7.dist-info/WHEEL
panisa-0.1.7.dist-info/top_level.txt
panisa-0.1.7.dist-info/RECORD
