Metadata-Version: 2.1
Name: panisa
Version: 0.1.7
Summary: panISa is a software to search insertion sequence (IS) on resequencing data (bam file)
Home-page: https://github.com/bvalot/panISa
Author: Benoit Valot
Author-email: benoit.valot@univ-fcomte.fr
Keywords: bioinformatic IS bacteria
Classifier: Development Status :: 5 - Production/Stable
Classifier: Intended Audience :: Science/Research
Classifier: Topic :: Scientific/Engineering :: Bio-Informatics
Classifier: License :: OSI Approved :: GNU General Public License v3 (GPLv3)
Classifier: Programming Language :: Python :: 3
Classifier: Programming Language :: Python :: 3.7
License-File: LICENSE
Requires-Dist: pysam >=0.9
Requires-Dist: requests >=2.12
